fileops/__init__.py
fileops/logger.py
fileops/pathutils.py
fileops/cached/__init__.py
fileops/cached/intermediate_step.py
fileops/export/__init__.py
fileops/export/_bioformats.py
fileops/export/_openvdb.py
fileops/export/_param_override.py
fileops/export/_vtk.py
fileops/export/_vtk_state.py
fileops/export/config.py
fileops/export/vtk_state.tmpl
fileops/image/__init__.py
fileops/image/_base.py
fileops/image/_bleach_correction.py
fileops/image/_image_file_bioio_ome.py
fileops/image/_image_file_ome.py
fileops/image/_image_file_tiffile_ome.py
fileops/image/_mmagellan.py
fileops/image/_mmagellan_position_stack.py
fileops/image/_mmanager_folder_series.py
fileops/image/_mmanager_metadata.py
fileops/image/_mmanager_single_stack.py
fileops/image/_nikon_elements_bioio.py
fileops/image/_ome.py
fileops/image/_pycromanager_single_stack.py
fileops/image/_tifffile_imagej_metadata.py
fileops/image/_tifffile_metadata.py
fileops/image/exceptions.py
fileops/image/factory.py
fileops/image/image_file.py
fileops/image/image_file_imagej.py
fileops/image/imagemeta.py
fileops/image/to_8bit.py
fileops/image/volocity.py
fileops/image/ops/__init__.py
fileops/image/ops/_z_projection.py
fileops/image/ops/_z_projection_types.py
fileops/loaders/__init__.py
fileops/loaders/tiff_loader.py
fileops/mixins/__init__.py
fileops/mixins/parameter_mixin.py
fileops/mixins/save_mixin.py
fileops/scripts/_config_edit.py
fileops/scripts/_config_generate.py
fileops/scripts/_config_update.py
fileops/scripts/_utils.py
fileops/scripts/config.py
fileops/scripts/reorder_axes.py
fileops/scripts/reorder_axes.svg
fileops/scripts/summary.py
imgfileops-0.3.0.dist-info/METADATA
imgfileops-0.3.0.dist-info/WHEEL
imgfileops-0.3.0.dist-info/entry_points.txt
imgfileops-0.3.0.dist-info/licenses/LICENSE.txt
imgfileops-0.3.0.dist-info/RECORD
