Metadata-Version: 2.4
Name: imgfileops
Version: 0.3.0
Summary: This package makes easy to replicate figures and movies from microscopy data from configuration files.
Project-URL: Homepage, https://github.com/fabio-echegaray/fileops
Project-URL: Bug Reports, https://github.com/fabio-echegaray/fileops/issues
Project-URL: Source, https://github.com/fabio-echegaray/fileops
Author-email: Fabio Rodrigo Echegaray Iturra <fabio.echegaray@gmail.com>
Maintainer-email: Fabio Rodrigo Echegaray Iturra <fabio.echegaray@gmail.com>
License-Expression: AGPL-3.0
License-File: LICENSE.txt
Keywords: micro-manager,microscopy,reader,render
Classifier: Development Status :: 3 - Alpha
Classifier: Intended Audience :: Developers
Classifier: Intended Audience :: Science/Research
Classifier: License :: OSI Approved :: GNU Affero General Public License v3
Classifier: Operating System :: OS Independent
Classifier: Programming Language :: Python :: 3
Classifier: Programming Language :: Python :: 3 :: Only
Classifier: Programming Language :: Python :: 3.9
Classifier: Programming Language :: Python :: 3.10
Classifier: Programming Language :: Python :: 3.11
Requires-Python: >=3.9
Requires-Dist: beautifulsoup4>=4.0.0
Requires-Dist: bioio-nd2>=1.5.0
Requires-Dist: bioio-ome-tiff~=1.4.0
Requires-Dist: bioio~=3.0.0
Requires-Dist: czifile>=2019.7.2
Requires-Dist: future>=0.18.0
Requires-Dist: lmfit>=1.3.1
Requires-Dist: matplotlib>=3.4
Requires-Dist: numpy<2.0.0,>=1.24
Requires-Dist: openpyxl>=3.0.0
Requires-Dist: pandas-ods-reader>=1.0
Requires-Dist: pandas>=1.2
Requires-Dist: pycromanager>=0.32
Requires-Dist: pyjavaz~=1.2.4
Requires-Dist: pytrackmate>=1.3.4
Requires-Dist: pyyaml>=5.4.1
Requires-Dist: roifile>=2023
Requires-Dist: scikit-image>=0.18
Requires-Dist: scipy>=1.10
Requires-Dist: shapely>=1.7.1
Requires-Dist: tifffile>=2023
Requires-Dist: typer>=0.9.0
Requires-Dist: vtk>9.2.0
